portgraph/__init__.py
portgraph/portgraph.py
portgraph-0.0.2.dist-info/LICENSE
portgraph-0.0.2.dist-info/METADATA
portgraph-0.0.2.dist-info/WHEEL
portgraph-0.0.2.dist-info/entry_points.txt
portgraph-0.0.2.dist-info/top_level.txt
portgraph-0.0.2.dist-info/RECORD
