Metadata-Version: 2.1
Name: portgraph
Version: 0.0.2
Summary: Create a graph for a(ll) FreeBSD port(s).
Home-page: https://gitlab.com/lbartoletti/portgraph/
Author: Loïc Bartoletti
Author-email: lbartoletti@tuxfamily.org
License: LICENSE
License-File: LICENSE
Requires-Dist: graphviz >=0.8.2
